mplot/__init__.py
mplot/color.py
mplot/createdate.py
mplot/example_of_mplot.py
mplot/plot.py
mplot-0.220004.dist-info/METADATA
mplot-0.220004.dist-info/WHEEL
mplot-0.220004.dist-info/top_level.txt
mplot-0.220004.dist-info/RECORD
