Metadata-Version: 2.1
Name: mplot
Version: 0.220004
Summary: This is a plotting library designed to be similar in usage to maple
Home-page: UNKNOWN
Author: Steve Mohr
Author-email: steve.h.mohr@gmail.com
License: UNKNOWN
Platform: UNKNOWN
